setup.cfg
setup.py
scrapy_sqs_pipeline.egg-info/PKG-INFO
scrapy_sqs_pipeline.egg-info/SOURCES.txt
scrapy_sqs_pipeline.egg-info/dependency_links.txt
scrapy_sqs_pipeline.egg-info/requires.txt
scrapy_sqs_pipeline.egg-info/top_level.txt
sqspipeline/__init__.py