Metadata-Version: 1.0
Name: scrapy-sqs-pipeline
Version: 0.1.1
Summary: Write scraped items to Amazon SQS.
Home-page: https://github.com/ziplokk1/botopipeline
Author: Mark Sanders
Author-email: sdscdeveloper@gmail.com
License: LICENSE.txt
Platform: UNKNOWN
